<?xml version="1.0" encoding="UTF-8" standalone="yes"?>
<map>
	<group name="Wreck_UH1Y" pos="12010.706055 138.750336 12411.241211" rpy="-0.000000 -0.000000 0.000000" a="90"/>
	<group name="Land_Mil_Barracks1" pos="12000.599609 142.240997 12493.599609" rpy="0.000000 0.000000 20.499996" a="69.5"/>
	<group name="Land_Mil_Barracks1" pos="11996.099609 142.240997 12481.599609" rpy="0.000000 0.000000 20.499996" a="69.5"/>
	<group name="Land_Mil_Barracks1" pos="12005.000000 142.240997 12505.299805" rpy="0.000000 0.000000 20.499996" a="69.5"/>
	<group name="Land_Mil_Barracks1" pos="12034.599609 142.240997 12494.400391" rpy="0.000000 0.000000 -159.999939" a="-110"/>
	<group name="Land_Mil_Barracks1" pos="12030.400391 142.240997 12482.599609" rpy="0.000000 0.000000 -159.999939" a="-110"/>
	<group name="Land_Wreck_offroad02_aban2_DE" pos="12019.599609 141.639008 12500.400391" rpy="0.000000 0.000000 0.000000" a="90"/>
	<group name="Land_Mil_Barracks1" pos="12025.599609 142.240997 12470.299805" rpy="0.000000 0.000000 -159.999939" a="-110"/>
	<group name="StaticObj_Dead_MassGrave_8m" pos="12025.267578 140.802963 12413.253906" rpy="0.000000 0.000000 18.499990" a="71.5"/>
	<group name="StaticObj_Dead_MassGrave_15m" pos="12023.400391 140.850006 12408.599609" rpy="0.000000 -1.999861 19.500000" a="70.5"/>
	<group name="Land_Container_1Mo" pos="12017.719727 141.168915 12465.409180" rpy="0.000000 0.000000 -69.999992" a="160"/>
	<group name="StaticObj_Dead_MassGrave_15m" pos="12023.141602 140.793213 12408.502930" rpy="0.000000 -1.999841 19.500002" a="70.5"/>
	<group name="Land_Container_1Mo" pos="12016.878906 141.168961 12463.117188" rpy="0.000000 0.000000 -69.999992" a="160"/>
	<group name="Land_Container_1Mo" pos="12016.041992 141.168961 12460.834961" rpy="0.000000 0.000000 -69.999992" a="160"/>
	<group name="Land_Container_1Mo_DE" pos="12021.562500 141.168945 12458.817383" rpy="0.000000 0.000000 -69.999992" a="160"/>
	<group name="Land_Container_1Mo_DE" pos="12022.393555 141.168961 12461.143555" rpy="0.000000 0.000000 -69.999992" a="160"/>
	<group name="Land_Container_1Mo_DE" pos="12023.206055 141.168915 12463.476563" rpy="0.000000 0.000000 -69.999992" a="160"/>
	<group name="Land_Container_1Mo" pos="12018.099609 143.668976 12460.099609" rpy="0.000000 0.000000 -69.999992" a="160"/>
	<group name="Land_Container_1Mo" pos="12019.000000 143.668976 12462.400391" rpy="0.000000 0.000000 -69.999992" a="160"/>
	<group name="Land_Container_1Mo" pos="12019.799805 143.668976 12464.700195" rpy="0.000000 0.000000 -69.999992" a="160"/>
	<group name="Land_Mil_Barracks6" pos="12057.299805 139.535995 12477.099609" rpy="0.000000 0.000000 -157.499939" a="-112.5"/>
	<group name="Land_Mil_Barracks6" pos="12077.299805 140.035995 12461.200195" rpy="0.000000 0.000000 -66.499985" a="156.5"/>
	<group name="StaticObj_Wreck_Bulldozer" pos="12035.447266 141.710724 12405.523438" rpy="-0.000000 -0.000000 0.000000" a="90"/>
	<group name="Land_Mil_Barracks6" pos="12050.400391 140.035995 12463.099609" rpy="0.000000 0.000000 21.499992" a="68.5"/>
	<group name="Land_Mil_Airfield_HQ" pos="12101.700195 145.550003 12465.400391" rpy="0.000000 0.000000 -68.500008" a="158.5"/>
	<group name="Land_Mil_Airfield_HQ" pos="12094.000000 145.550003 12445.000000" rpy="0.000000 0.000000 -68.500008" a="158.5"/>
	<group name="Land_Container_1Mo" pos="12099.299805 149.334976 12460.299805" rpy="0.000000 0.000000 19.500000" a="70.5"/>
	<group name="Land_Container_1Mo" pos="12095.799805 149.168976 12449.599609" rpy="0.000000 0.000000 19.500000" a="70.5"/>
	<group name="Land_Container_1Mo" pos="12098.099609 151.799973 12454.599609" rpy="0.000000 0.000000 19.500000" a="70.5"/>
	<group name="Land_Container_1Aoh" pos="12108.700195 141.668976 12472.821289" rpy="-87.999992 0.000000 -68.500008" a="158.5"/>
	<group name="StaticObj_Dead_MassGrave_15m" pos="12022.018555 141.269516 12404.172852" rpy="0.000000 0.000000 19.499983" a="70.5"/>
	<group name="StaticObj_Dead_MassGrave_15m" pos="12020.500000 141.013000 12399.200195" rpy="0.000000 0.000000 19.500000" a="70.5"/>
	<group name="StaticObj_Dead_MassGrave_15m" pos="12018.900391 141.220993 12393.900391" rpy="0.000000 0.000000 19.500000" a="70.5"/>
	<group name="StaticObj_Dead_MassGrave_15m" pos="12017.400391 141.365997 12388.000000" rpy="0.000000 -1.499987 19.499985" a="70.5"/>
	<group name="StaticObj_Dead_MassGrave_15m" pos="11999.799805 142.098007 12395.400391" rpy="0.000000 0.000000 19.500000" a="70.5"/>
	<group name="StaticObj_Dead_MassGrave_15m" pos="12002.299805 141.707993 12400.900391" rpy="0.000000 0.000000 19.500004" a="70.5"/>
	<group name="StaticObj_Dead_MassGrave_15m" pos="12004.200195 141.389999 12405.900391" rpy="0.000000 0.000000 19.500002" a="70.5"/>
	<group name="StaticObj_Dead_MassGrave_15m" pos="12004.900391 141.041000 12410.299805" rpy="0.000000 0.000000 19.500000" a="70.5"/>
	<group name="StaticObj_Dead_MassGrave_15m" pos="12006.881836 141.204895 12414.395508" rpy="0.000000 0.000000 19.499983" a="70.5"/>
	<group name="Land_Wreck_offroad02_aban2_DE" pos="12016.900391 141.778000 12494.799805" rpy="0.000000 0.000000 -53.499989" a="143.5"/>
	<group name="Wreck_UH1Y" pos="12018.200195 134.735992 12392.900391" rpy="0.000000 0.000000 0.000000" a="90"/>
	<group name="Land_Airfield_ServiceHangar_R" pos="12195.599609 140.294022 12674.000000" rpy="0.000000 0.000000 108.999985" a="-19"/>
	<group name="Land_Airfield_ServiceHangar_L" pos="12149.099609 140.294022 12689.299805" rpy="0.000000 0.000000 107.499992" a="-17.5"/>
	<group name="Land_Wreck_C130J_Cargo" pos="12138.200195 144.787003 12643.099609" rpy="0.000000 0.000000 -76.799988" a="166.8"/>
	<group name="Land_Mil_ATC_Big" pos="12089.000000 155.897995 12565.000000" rpy="0.000000 0.000000 112.499992" a="-22.5"/>
	<group name="Land_Tisy_RadarPlatform_Top" pos="11950.500000 148.641998 12719.400391" rpy="0.000000 0.000000 28.499990" a="61.5"/>
	<group name="StaticObj_Tisy_RadarPlatform_Mid" pos="11934.700195 147.875000 12689.700195" rpy="0.000000 0.000000 27.399990" a="62.6"/>
	<group name="StaticObj_Tisy_RadarPlatform_Bot" pos="11917.700195 144.889999 12657.000000" rpy="0.000000 0.000000 27.499998" a="62.5"/>
	<group name="Wreck_UH1Y" pos="11951.000000 157.856003 12719.299805" rpy="0.000000 0.000000 0.000000" a="90"/>
	<group name="Land_Wreck_C130J" pos="11893.400391 145.587006 12615.599609" rpy="0.000000 0.000000 118.499992" a="-28.5"/>
	<group name="Land_Mil_Barracks_Round" pos="12035.700195 141.070007 12433.299805" rpy="0.000000 0.000000 -58.500000" a="148.5"/>
	<group name="Land_Mil_Barracks_Round" pos="12039.099609 141.070007 12438.900391" rpy="0.000000 0.000000 -58.500000" a="148.5"/>
</map>
